{
    "Alhué": {
        "topic_0": 0,
        "topic_1": 0,
        "topic_2": 0,
        "topic_3": 0
    },
    "Buin": {
        "topic_0": 0,
        "topic_1": 0,
        "topic_2": 0.77,
        "topic_3": 0.21
    },
    "Calera de Tango": {
        "topic_0": 0,
        "topic_1": 0,
        "topic_2": 0,
        "topic_3": 0
    },
    "Cerrillos": {
        "topic_0": 0.02,
        "topic_1": 0.09,
        "topic_2": 0.75,
        "topic_3": 0.12
    },
    "Cerro Navia": {
        "topic_0": 0.01,
        "topic_1": 0.06,
        "topic_2": 0.55,
        "topic_3": 0.37
    },
    "Colina": {
        "topic_0": 0.05,
        "topic_1": 0.12,
        "topic_2": 0.7,
        "topic_3": 0.12
    },
    "Conchali": {
        "topic_0": 0.02,
        "topic_1": 0.15,
        "topic_2": 0.7,
        "topic_3": 0.12
    },
    "Curacaví": {
        "topic_0": 0.02,
        "topic_1": 0.05,
        "topic_2": 0.48,
        "topic_3": 0.43
    },
    "El Bosque": {
        "topic_0": 0.04,
        "topic_1": 0.1,
        "topic_2": 0.65,
        "topic_3": 0.21
    },
    "El Monte": {
        "topic_0": 0.14,
        "topic_1": 0,
        "topic_2": 0.86,
        "topic_3": 0
    },
    "Estación Central": {
        "topic_0": 0.02,
        "topic_1": 0.08,
        "topic_2": 0.7,
        "topic_3": 0.19
    },
    "Huechuraba": {
        "topic_0": 0.08,
        "topic_1": 0.13,
        "topic_2": 0.62,
        "topic_3": 0.16
    },
    "Independencia": {
        "topic_0": 0.05,
        "topic_1": 0.1,
        "topic_2": 0.69,
        "topic_3": 0.14
    },
    "Isla de Maipo": {
        "topic_0": 0,
        "topic_1": 0,
        "topic_2": 0,
        "topic_3": 0
    },
    "La Cisterna": {
        "topic_0": 0.05,
        "topic_1": 0.03,
        "topic_2": 0.57,
        "topic_3": 0.34
    },
    "La Florida": {
        "topic_0": 0.08,
        "topic_1": 0.06,
        "topic_2": 0.65,
        "topic_3": 0.19
    },
    "La Granja": {
        "topic_0": 0.14,
        "topic_1": 0.02,
        "topic_2": 0.78,
        "topic_3": 0.05
    },
    "La Pintana": {
        "topic_0": 0,
        "topic_1": 0.12,
        "topic_2": 0.71,
        "topic_3": 0.16
    },
    "La Reina": {
        "topic_0": 0.05,
        "topic_1": 0.08,
        "topic_2": 0.65,
        "topic_3": 0.21
    },
    "Lampa": {
        "topic_0": 0.03,
        "topic_1": 0.03,
        "topic_2": 0.76,
        "topic_3": 0.17
    },
    "Las Condes": {
        "topic_0": 0.05,
        "topic_1": 0.11,
        "topic_2": 0.7,
        "topic_3": 0.14
    },
    "Lisbon": {
        "topic_0": 0,
        "topic_1": 0,
        "topic_2": 0,
        "topic_3": 0
    },
    "Lo Barnechea": {
        "topic_0": 0.04,
        "topic_1": 0.1,
        "topic_2": 0.65,
        "topic_3": 0.19
    },
    "Lo Espejo": {
        "topic_0": 0.04,
        "topic_1": 0.01,
        "topic_2": 0.93,
        "topic_3": 0
    },
    "Lo Prado": {
        "topic_0": 0.04,
        "topic_1": 0.1,
        "topic_2": 0.58,
        "topic_3": 0.27
    },
    "Macul": {
        "topic_0": 0.08,
        "topic_1": 0.1,
        "topic_2": 0.71,
        "topic_3": 0.1
    },
    "Maipú": {
        "topic_0": 0.04,
        "topic_1": 0.12,
        "topic_2": 0.63,
        "topic_3": 0.2
    },
    "María Pinto": {
        "topic_0": 0,
        "topic_1": 0,
        "topic_2": 0,
        "topic_3": 0
    },
    "Melipilla": {
        "topic_0": 0.2,
        "topic_1": 0,
        "topic_2": 0.45,
        "topic_3": 0.34
    },
    "Padre Hurtado": {
        "topic_0": 0,
        "topic_1": 0.21,
        "topic_2": 0.76,
        "topic_3": 0.01
    },
    "Paine": {
        "topic_0": 0.01,
        "topic_1": 0.01,
        "topic_2": 0.97,
        "topic_3": 0.01
    },
    "Pedro Aguirre Cerda": {
        "topic_0": 0.01,
        "topic_1": 0.11,
        "topic_2": 0.56,
        "topic_3": 0.3
    },
    "Peñaflor": {
        "topic_0": 0.04,
        "topic_1": 0.03,
        "topic_2": 0.72,
        "topic_3": 0.2
    },
    "Peñalolén": {
        "topic_0": 0.1,
        "topic_1": 0.08,
        "topic_2": 0.58,
        "topic_3": 0.23
    },
    "Pirque": {
        "topic_0": 0,
        "topic_1": 0,
        "topic_2": 0,
        "topic_3": 0
    },
    "Providencia": {
        "topic_0": 0.06,
        "topic_1": 0.1,
        "topic_2": 0.68,
        "topic_3": 0.15
    },
    "Pudahuel": {
        "topic_0": 0.05,
        "topic_1": 0.09,
        "topic_2": 0.69,
        "topic_3": 0.15
    },
    "Puente Alto": {
        "topic_0": 0.06,
        "topic_1": 0.1,
        "topic_2": 0.6,
        "topic_3": 0.23
    },
    "Quilicura": {
        "topic_0": 0.06,
        "topic_1": 0.04,
        "topic_2": 0.66,
        "topic_3": 0.23
    },
    "Quinta Normal": {
        "topic_0": 0.07,
        "topic_1": 0.07,
        "topic_2": 0.68,
        "topic_3": 0.18
    },
    "Recoleta": {
        "topic_0": 0.05,
        "topic_1": 0.11,
        "topic_2": 0.74,
        "topic_3": 0.1
    },
    "Renca": {
        "topic_0": 0.1,
        "topic_1": 0.08,
        "topic_2": 0.64,
        "topic_3": 0.17
    },
    "San Bernardo": {
        "topic_0": 0.05,
        "topic_1": 0.1,
        "topic_2": 0.59,
        "topic_3": 0.25
    },
    "San Joaquí­n": {
        "topic_0": 0.04,
        "topic_1": 0.02,
        "topic_2": 0.68,
        "topic_3": 0.26
    },
    "San José de Maipo": {
        "topic_0": 0,
        "topic_1": 0.15,
        "topic_2": 0.58,
        "topic_3": 0.25
    },
    "San Miguel": {
        "topic_0": 0.05,
        "topic_1": 0.1,
        "topic_2": 0.57,
        "topic_3": 0.28
    },
    "San Pedro": {
        "topic_0": 0,
        "topic_1": 0.19,
        "topic_2": 0.3,
        "topic_3": 0.49
    },
    "San Ramón": {
        "topic_0": 0.05,
        "topic_1": 0.05,
        "topic_2": 0.76,
        "topic_3": 0.13
    },
    "Santiago": {
        "topic_0": 0.06,
        "topic_1": 0.06,
        "topic_2": 0.68,
        "topic_3": 0.19
    },
    "Talagante": {
        "topic_0": 0.05,
        "topic_1": 0.09,
        "topic_2": 0.75,
        "topic_3": 0.11
    },
    "Tiltil": {
        "topic_0": 0,
        "topic_1": 0,
        "topic_2": 0.68,
        "topic_3": 0.3
    },
    "Villa San Antonio de Comaico": {
        "topic_0": 0,
        "topic_1": 0,
        "topic_2": 0,
        "topic_3": 0
    },
    "Vitacura": {
        "topic_0": 0.07,
        "topic_1": 0.12,
        "topic_2": 0.62,
        "topic_3": 0.18
    },
    "Ñuñoa": {
        "topic_0": 0.05,
        "topic_1": 0.1,
        "topic_2": 0.66,
        "topic_3": 0.18
    }
}